Workbook

Sheet P&L - Standalone
A1: Particulars | B1: Cogencis Field | C1: Field id
A2: Income | B2: Lable
A3: Revenue From Operations | B3: Gross Sales/Income from Operations | C3: 256
A4: Other Income | B4: Miscellaneous Income | C4: 265
A5: Total Income | B5: Total Income | C5: 25238
A6: Expenses | B6: Lable
A7: Cost of materials consumed | B7: Cost of Materials Consumed | C7: 230
A8: Purchases of stock-in-trade | B8: Purchase of Stock-in-Trade | C8: 307
A9: Changes in inventories of finished goods, work-in-progress and stock-in-trade | B9: Changes in Inventories of Finished Goods, Work-In-Progress and Stock-In-Trade | C9: 227
A10: Finance Cost | B10: Finance Costs | C10: 246
A11: Employee Benefits Expenses | B11: Employee Benefit Expense | C11: 238
A12: Depreciation and amortisation expense | B12: Depreciation, Depletion and Amortisation Expense | C12: 232
A13: Other expenses (Any item exceeding of the total expenses relating to continuing operations to be shown seoaratelv) | B13: Other Expenses | C13: 279
A14: Total Expenses | B14: Total Expenses | C14: 320
A15: Profit / (Loss) before exceptional items and tax | B15: Profit/(Loss) from Ordinary Activities after Finance Costs but before Exceptional Items | C15: 294
A16: Exceptional Items | B16: Other Exceptional Items | C16: 278
A17: Total Exceptional Items | B17: Total Exceptional Items | C17: 319
A18: Profit / (loss) before tax | B18: Profit/(Loss) From Ordinary Activities before Tax | C18: 296
A19: Tax Expenses | B19: Lable
A20: Current Tax | B20: Tax Expense | C20: 318
A21: Deferred Tax | B21: Deferred Tax | C21: 231
A22: Total Tax Expenses | B22: Lable
A23: Profit/(Loss) for a period from continuing operations | B23: Profit/(Loss) for the Period from Continuing Operations | C23: 20017
A24: Profit/ (Loss) for a period from discontinuing operations | B24: Profit/(Loss) from Discontinuing Operations | C24: 20016
A25: Tax Expenses of discountined operations | B25: Tax Expense of Discontinuing Operations | C25: 20018
A26: Profit/ (Loss) for a period from discontinuing operations (after tax) | B26: Net Profit From Discontinuing Operations (After Tax) | C26: 20015
A27: Other Comprehensive Income/ (Loss) | B27: Lable
A28: Amount of items that will not be reclassified to profit or loss | B28: Items that will not be reclassified to Profit or Loss | C28: 22293
A29: Income tax relating to items that will not be reclassified to profit or loss | B29: Income Tax related to items that will not be reclassified to Profit or Loss | C29: 22295
A30: Amount of items that will be reclassified to profit or loss | B30: Items that will be reclassified to Profit or Loss | C30: 22294
A31: Income tax relating to items that will be reclassified to profit or loss | B31: Income Tax related to items that will be reclassified to Profit or Loss | C31: 22296
A32: Total Comprehensive income for the period (comprising profit/loss) and other comprehensive income for the period) | B32: Total Comprehensive Gain (Loss) For the Year | C32: 20019
A33: Paid -up Equity Share Capital (Face Value of Re.1/- each) | B33: Paid-Up Equity Share Capital | C33: 282
A34: Earnings Per Share (For continuing operations) | B34: Lable
A35: Basic | B35: Basic EPS | C35: 222
A36: Diluted | B36: Diluted EPS | C36: 234

Sheet P&L_Consolidated
A1: Particulars | B1: Cogencis Field | C1: Field id
A2: Income | B2: Lable
A3: Revenue From Operations | B3: Gross Sales/Income from Operations | C3: 256
A4: Other Income | B4: Miscellaneous Income | C4: 265
A5: Total Income | B5: Total Income | C5: 25238
A6: Expenses | B6: Lable
A7: Cost of materials consumed | B7: Cost of Materials Consumed | C7: 230
A8: Purchases of stock-in-trade | B8: Purchase of Stock-in-Trade | C8: 307
A9: Changes in inventories of finished goods, work-in- progress and stock-in-trade | B9: Changes in Inventories of Finished Goods, Work-In-Progress and Stock-In-Trade | C9: 227
A10: Finance Cost | B10: Finance Costs | C10: 246
A11: Employee Benefits Expenses | B11: Employee Benefit Expense | C11: 238
A12: Depreciation and amortisation expense | B12: Depreciation, Depletion and Amortisation Expense | C12: 232
A13: Other expenses (Any item exceeding 10% of the total expenses relating to continuing operations to be shown separately) | B13: Other Expenses | C13: 279
A14: Total Expenses | B14: Total Expenses | C14: 320
A15: Profit I (Loss) before exceptional items and tax | B15: Profit/(Loss) from Ordinary Activities after Finance Costs but before Exceptional Items | C15: 294
A16: Exceptional Items | B16: Other Exceptional Items | C16: 278
A17: Total Exceptional Items | B17: Total Exceptional Items | C17: 319
A18: Profit I (Loss) before tax | B18: Profit/(Loss) From Ordinary Activities before Tax | C18: 296
A19: Tax Expenses | B19: Lable
A20: Current Tax | B20: Tax Expense | C20: 318
A21: Deferred Tax | B21: Deferred Tax | C21: 231
A22: Total Tax Expenses | B22: Lable
A23: Profit/ (Loss) for a period from continuing operations | B23: Profit/(Loss) for the Period from Continuing Operations | C23: 20017
A24: Profit/ (Loss) for a period from dis -continuing operations | B24: Profit/(Loss) from Discontinuing Operations | C24: 20016
A25: Tax Expenses of discountined operations | B25: Tax Expense of Discontinuing Operations | C25: 20018
A26: Profit/ (Loss) for a period from dis -continuing operations (after tax) | B26: Net Profit From Discontinuing Operations (After Tax) | C26: 20015
A27: Other Comprehensive Income/ (Loss) | B27: Lable
A28: Amount of items that will not be reclassified to profit or loss | B28: Items that will not be reclassified to Profit or Loss | C28: 22293
A29: Income tax relating to items that will not be reclassified to profit or loss | B29: Income Tax related to items that will not be reclassified to Profit or Loss | C29: 22295
A30: Amount of items that will be reclassified to profit or loss | B30: Items that will be reclassified to Profit or Loss | C30: 22294
A31: Income tax relating to items that will be reclassified to profit or loss | B31: Income Tax related to items that will be reclassified to Profit or Loss | C31: 22296
A32: Total Comprehensive income for the period (comprising profit/loss) and other comprehensive income for the period) | B32: Total Comprehensive Gain (Loss) For the Year | C32: 20019
A33: Paid -up Equity Share Capital (Face Value of Rs.1/- each | B33: Paid-Up Equity Share Capital | C33: 282
A34: Earnings Per Share (For continuing operations) | B34: Lable
A35: Basic | B35: Basic EPS | C35: 222
A36: Diluted | B36: Diluted EPS | C36: 234

Sheet BS_Standalone
A1: Particulars | B1: Cogencis Field | C1: Field id
A2: ASSETS | B2: Lable
A3: Non-Current Assets | B3: Lable
A4: Property plant and equipment | B4: Property, Plant & Equipment | C4: 20222
A5: Capital work-in-progress | B5: Capital Work-In-Progress | C5: 13720
A6: Investment property | B6: Investment Property | C6: 25736
A7: Goodwill | B7: Goodwill | C7: 20220
A8: Other intangible assets | B8: Other Intangible Assets | C8: 20221
A9: Intangible assets under development | B9: Intangible assets under development | C9: 13736
A10: Biological assets other than bearer plants | B10: Biological Assets other than bearer plants | C10: 20219
A11: Investments accounted for using equity method | B11: Investment accounted for using Equity method
A12: Total | B12: Lable
A13: Non- Current Financial Assets | B13: Lable
A14: Non-current investments | B14: Non-Current Investments | C14: 13748
A15: Trade receivables, non-current | B15: Trade Receivables | C15: 20218
A16: Loans, non-current | B16: Loans Non-Current | C16: 20217
A17: Other non-current financial assets | B17: Other Non-Current Financial Assets | C17: 20216
A18: Total non-current financial assets
A19: Deferred tax assets (net) | B19: Deferred Tax Assets (Net) | C19: 13726
A20: Other non-current assets | B20: Other Non-Current Assets | C20: 13753
A21: Total non-current Assets | B21: Total Non-Current Assets | C21: 13777
A22: Current assets | B22: Lable
A23: Inventories | B23: Inventories | C23: 13737
A24: Current financial asset | B24: Lable
A25: Current investments | B25: Current Investments | C25: 13724
A26: Trade receivables, current | B26: Trade Receivables | C26: 13780
A27: Cash and cash equivalents | B27: Cash And Cash Equivalents | C27: 13722
A28: Bank balance other than cash and cash equivalents | B28: Bank balance other than cash and cash equivalents | C28: 29788
A29: Loans, current | B29: Loans, Current | C29: 20230
A30: Other current financial assets | B30: Other Current Financial Assets | C30: 20231
A31: Total current financial assets
A32: Current tax assets (net) | B32: Current Tax Assets (Net) | C32: 20228
A33: Other current assets | B33: Other Current Assets | C33: 13750
A34: Total Current Assets | B34: Total Current Assets | C34: 13774
A35: Non-current assets classified as held for sale | B35: Assets classified as held for sale | C35: 20208
A36: Regulatory deferral account debit balances and related deferred tax Assets | B36: Regulatory Deferral Account Debit Balances and Related Deferred Tax Assets | C36: 33087
A37: Total Assets | B37: Total Assets | C37: 13771
A38: Equity and liabilities | B38: Lable
A39: Equity | B39: Lable
A40: Equity attributable to owners of parent | B40: Lable
A41: Equity share capital | B41: Share Capital | C41: 13765
A42: Other equity | B42: Reserves And Surplus/Other Equity | C42: 13762
A43: Total equity attributable to owners of parent
A44: Non-controlling interest | B44: Non-controlling interest
A45: Total Equity | B45: Total Share Holder's Funds | C45: 13773
A46: Liabilities | B46: Lable
A47: Non-current liabilities | B47: Lable
A48: Non-current financial liabilities | B48: Lable
A49: Borrowings, non-current | B49: Borrowings | C49: 20223
A50: Trade payables, non-current | B50: Trade Payables | C50: 20227
A51: Other non-current financial liabilities | B51: Other Non Current Financial Liabilities | C51: 20226
A52: Total non-current financial liabilities
A53: Provisions, non-current | B53: Long-Term Provisions | C53: 13743
A54: Deferred tax liabilities (net) | B54: Deferred Tax Liability (Net) | C54: 13727
A55: Deferred government grants, Non-current | B55: Deferred government grants, Non-current | C55: 33070
A56: Other non-current liabilities | B56: Other Non-Current Liabilities | C56: 26449
A57: Total non-current liabilities | B57: Total Non-Current Liabilities | C57: 13778
A58: Current Liabilities | B58: Lable
A59: Current financial liabilities | B59: Lable
A60: Borrowings, current | B60: Borrowings | C60: 20209
A61: Trade payables, current | B61: Trade Payables | C61: 13779
A62: Other current financial liabilities | B62: Other Current Financial Liabilities | C62: 20214
A63: Total current financial liabilities
A64: Other current liabilities | B64: Other liabilities | C64: 26450
A65: Provisions, current | B65: Short-Term Provisions | C65: 13767
A66: Current tax liabilities (Net) | B66: Current Tax Liabilities (Net) | C66: 20211
A67: Deferred government grants, Current | B67: Deferred government grants, Current | C67: 33069
A68: Total Current Liabilities | B68: Total Current Liabilities | C68: 13775
A69: Liabilities directly associated with assets in disposal group classified as held for sale | B69: Liabilities directly associated with assets in disposal group classified as held for sale | C69: 25685
A70: Regulatory deferral account credit balances and related deferred tax liability | B70: Regulatory deferral account credit balances and related deferred tax liability | C70: 33088
A71: Total Liabilities
A72: Total Equity and Liabilites | B72: Total Equity And Liabilities | C72: 13776

Sheet BS_Consolidated
A1: Particulars | B1: Cogencis Field | C1: Field id
A2: ASSETS | B2: Lable
A3: Non-Current Assets | B3: Lable
A4: Property, plant and equipment | B4: Property, Plant & Equipment | C4: 20222
A5: Capital work-in-progress | B5: Capital Work-In-Progress | C5: 13720
A6: Investment property | B6: Investment Property | C6: 25736
A7: Goodwill | B7: Goodwill On Consolidation | C7: 13734
A8: Other intangible assets | B8: Other Intangible Assets | C8: 20221
A9: Intangible assets under development | B9: Intangible assets under development | C9: 13736
A10: Biological assets other than bearer plants | B10: Biological Assets other than bearer plants | C10: 20219
A11: Investments accounted for using equity method | B11: Investment accounted for using Equity method
A12: Non- Current Financial Assets | B12: Lable
A13: Non-current investments | B13: Non-Current Investments | C13: 13748
A14: Trade receivables, non-current | B14: Trade Receivables | C14: 20218
A15: Loans, non-current | B15: Loans Non-Current | C15: 20217
A16: Other non-current financial assets | B16: Other Non-Current Financial Assets | C16: 20216
A17: Total non-current financial assets
A18: Deferred tax assets (net) | B18: Deferred Tax Assets (Net) | C18: 13726
A19: Other non-current assets | B19: Other Non-Current Assets | C19: 13753
A20: Total Non-Current Assets | B20: Total Non-Current Assets | C20: 13777
A21: Current assets | B21: Lable
A22: Inventories | B22: Inventories | C22: 13737
A23: Current financial asset | B23: Lable
A24: Current investments | B24: Current Investments | C24: 13724
A25: Trade receivables, current | B25: Trade Receivables | C25: 13780
A26: Cash and cash equivalents | B26: Cash And Cash Equivalents | C26: 13722
A27: Bank balance other than cash and cash equivalents | B27: Bank balance other than cash and cash equivalents | C27: 29788
A28: Loans, current | B28: Loans, Current | C28: 20230
A29: Other current financial assets | B29: Other Current Financial Assets | C29: 20231
A30: Total current financial assets
A31: Current tax assets (net) | B31: Current Tax Assets (Net) | C31: 20228
A32: Other current assets | B32: Other Current Assets | C32: 13750
A33: Total Current Assets | B33: Total Current Assets | C33: 13774
A34: Non-current assets classified as held for sale | B34: Assets classified as held for sale | C34: 20208
A35: Regulatory deferral account debit balances and related deferred tax Assets | B35: Regulatory Deferral Account Debit Balances and Related Deferred Tax Assets | C35: 33087
A36: Total Assets | B36: Total Assets | C36: 13771
A37: Equity and liabilities | B37: Lable
A38: Equity | B38: Lable
A39: Equity attributable to owners of parent | B39: Lable
A40: Equity share capital | B40: Share Capital | C40: 13765
A41: Other equity | B41: Reserves And Surplus/Other Equity | C41: 13762
A42: Total equity attributable to owners of parent
A43: Non controlling interest | B43: Non controlling interest
A44: Total Equity | B44: Total Share Holder's Funds | C44: 13773
A45: Liabilities | B45: Lable
A46: Non-Current Liabilities | B46: Lable
A47: Non-current financial liabilities | B47: Lable
A48: Borrowings, non-current | B48: Borrowings | C48: 20223
A49: Trade payables, non-current | B49: Trade Payables | C49: 20227
A50: Other non-current financial liabilities | B50: Other Non Current Financial Liabilities | C50: 20226
A51: Total non-current financial liabilities
A52: Provisions, non-current | B52: Long-Term Provisions | C52: 13743
A53: Deferred tax liabilities (net) | B53: Deferred Tax Liability (Net) | C53: 13727
A54: Deferred government grants, Non-current | B54: Deferred government grants, Non-current | C54: 33070
A55: Other non-current liabilities | B55: Other Non-Current Liabilities | C55: 26449
A56: Total non-current liabilities | B56: Total Non-Current Liabilities | C56: 13778
A57: Current Liabilities | B57: Lable
A58: Current financial liabilities | B58: Lable
A59: Borrowings, current | B59: Borrowings | C59: 20209
A60: Trade payables, current | B60: Trade Payables | C60: 13779
A61: Other current financial liabilities | B61: Other Current Financial Liabilities | C61: 20214
A62: Total current financial liabilities
A63: Other current liabilities | B63: Other liabilities | C63: 26450
A64: Provisions, current | B64: Short-Term Provisions | C64: 13767
A65: Current tax liabilities (Net) | B65: Current Tax Liabilities (Net) | C65: 20211
A66: Deferred government grants, Current | B66: Deferred government grants, Current | C66: 33069
A67: Total current liabilities | B67: Total Current Liabilities | C67: 13775
A68: Liabilities directly associated with assets in disposal group classified as held for sale | B68: Liabilities directly associated with assets in disposal group classified as held for sale | C68: 25685
A69: Regulatory deferral account credit balances and related deferred tax liability | B69: Regulatory deferral account credit balances and related deferred tax liability | C69: 33088
A70: Total Liabilities
A71: Total Equity and Liabilities | B71: Total Equity And Liabilities | C71: 13776

Sheet CFS_Standalone
A1: Particulars | B1: Cogencis Field | C1: Field id
A2: Cash flow from operating activities | B2: =_xlfn.XLOOKUP(A2,[1]CFS_Standalone!$A:$A,[1]CFS_Standalone!$B:$B) -> Lable
A3: Profit/(Loss) before tax | B3: Net Profit Before Tax And Exceptional Item | C3: 17539
A4: Adjustments for: | B4: =_xlfn.XLOOKUP(A4,[1]CFS_Standalone!$A:$A,[1]CFS_Standalone!$B:$B) -> Lable
A5: Depreciation and amortization expense | B5: Depreciation and Amortisation Expense | C5: 30399
A6: Intrest Income | B6: Interest Income | C6: 30481
A7: Finance cost | B7: Interest Expense | C7: 30479
A8: Adjustment during the year
A9: Operating profits before working capital changes | B9: Lable
A10: Adjustments for changes in: | B10: Lable
A11: (Increase)/ Decrease in Trade receivables | B11: Trade And Other Receivables | C11: 30674
A12: (Increase)/ Decrease in Inventories | B12: Inventories | C12: 30487
A13: Increase/ (Decrease) in Loans | B13: Loans And Advances | C13: 30497
A14: (Increase)/ Decrease in other non current Financials asset | B14: Adjustments for other financial assets, non-current | C14: 30452
A15: (Increase)/ Decrease in other non current asset | B15: Other Current and Non Current Assets | C15: 30518
A16: (Increase)/ Decrease in other current financial asset | B16: Adjustments for other financial assets, current | C16: 30451
A17: (Increase)/ Decrease in other current asset | B17: Other Current and Non Current Assets | C17: 30518
A18: Increase/(Decrease) in Current Tax Asset (Net) | B18: Other Current and Non Current Assets | C18: 30518
A19: Increase/ (Decrease) in Trade payables | B19: Trade Payables And Others | C19: 30675
A20: Increase/(Decrease) in Provision | B20: Provisions | C20: 30627
A21: Increase/(Decrease) in other current Liabilities and Provision for expenses | B21: Other Current and Non Current Liabilities | C21: 30519
A22: Cash generated from operations | B22: Cash Generated From Operations | C22: 30372
... A24: Net cash inflow/(outflow) from operating activities | B24: Net Cash Flow From Operating Activities | C24: 17538
A25: Cash flow from investing activities | B25: Lable
A26: (Purchase) / Sales of non-current investments | B26: Sale Of Investments | C26: 17563
A27: (Purchase) / Sales of current investments | B27: Sale Of Investments | C27: 17563
A28: (Purchase) / Sales of Assets | B28: Sale Of Fixed Assets (Tangible / Intangible) | C28: 30662
A29: Interest Received/ Dividend Received | B29: Interest Received | C29: 30485
A30: Short term loans given | B30: Cash Advances and Loans Made to Other Parties | C30: 30368
A31: Net cash outflow from investing activities | B31: Net Cash Flow From Investing Activities | C31: 17537
A32: Cash Flow from Financing activities | B32: Lable
A33: Increase/(Decrease) in Short term borrowings | B33: Proceeds From Short Term Borrowings | C33: 17555
A34: Increase/(Decrease) in Long term borrowings | B34: Proceeds From Long Term Borrowings | C34: 17554
A35: Finance Cost paid | B35: Interest Paid | C35: 30484
A36: Intrest Income | B36: Others-Financing Activities | C36: 17543
A37: Loans and advances & others | B37: Others-Financing Activities | C37: 17543
A38: Net Adjustment in reserve & surplus for the year | B38: Transfer On Amalgamation | C38: 17566
A39: Net cash inflow/(outflow) from Financing activities | B39: Net Cash Flow From Financing Activities | C39: 17536
A40: Net Increase/(Decrease) in Cash and Cash Equivalents | B40: Net increase (decrease) in cash and cash equivalents before effect of exchange rate changes | C40: 30458
A41: Cash and cash equivalents at the beginning of the financial year | B41: Cash and Cash Equivalents at the Beginning of the Year | C41: 17519
A42: Cash and cash equivalents at the end of the financial year | B42: Cash and Cash Equivalents at the End of the Year | C42: 30371

Sheet CFS_Consolidated
A1: Particulars | B1: Cogencis Field | C1: Field id
A2: Cash flow from operating activities | B2: =_xlfn.XLOOKUP(A2,CFS_Standalone!A:A,CFS_Standalone!B:B) -> Lable
A3: Profit/(Loss) before tax | B3: =_xlfn.XLOOKUP(A3,CFS_Standalone!A:A,CFS_Standalone!B:B) -> Net Profit Before Tax And Exceptional Item | C3: =_xlfn.XLOOKUP(A3,CFS_Standalone!A:A,CFS_Standalone!C:C) -> 17539
A4: Adjustments for: | B4: =_xlfn.XLOOKUP(A4,CFS_Standalone!A:A,CFS_Standalone!B:B) -> Lable
A5: Depreciation and amortization expense | B5: =_xlfn.XLOOKUP(A5,CFS_Standalone!A:A,CFS_Standalone!B:B) -> Depreciation and Amortisation Expense | C5: =_xlfn.XLOOKUP(A5,CFS_Standalone!A:A,CFS_Standalone!C:C) -> 30399
A6: Finance income | B6: Interest Income | C6: 30481
A7: Finance cost | B7: =_xlfn.XLOOKUP(A7,CFS_Standalone!A:A,CFS_Standalone!B:B) -> Interest Expense | C7: =_xlfn.XLOOKUP(A7,CFS_Standalone!A:A,CFS_Standalone!C:C) -> 30479
A8: Adjustment during the year
A9: Operating profits before working capital changes | B9: =_xlfn.XLOOKUP(A9,CFS_Standalone!A:A,CFS_Standalone!B:B) -> Lable
A10: Adjustments for changes in: | B10: =_xlfn.XLOOKUP(A10,CFS_Standalone!A:A,CFS_Standalone!B:B) -> Lable
A11: (Increase)/ Decrease in Trade receivables | B11: =_xlfn.XLOOKUP(A11,CFS_Standalone!A:A,CFS_Standalone!B:B) -> Trade And Other Receivables | C11: =_xlfn.XLOOKUP(A11,CFS_Standalone!A:A,CFS_Standalone!C:C) -> 30674
A12: (Increase)/ Decrease in Inventories | B12: =_xlfn.XLOOKUP(A12,CFS_Standalone!A:A,CFS_Standalone!B:B) -> Inventories | C12: =_xlfn.XLOOKUP(A12,CFS_Standalone!A:A,CFS_Standalone!C:C) -> 30487
A13: Increase/ (Decrease) in Loans | B13: =_xlfn.XLOOKUP(A13,CFS_Standalone!A:A,CFS_Standalone!B:B) -> Loans And Advances | C13: =_xlfn.XLOOKUP(A13,CFS_Standalone!A:A,CFS_Standalone!C:C) -> 30497
A14: (Increase)/ Decrease in other non current asset | B14: =_xlfn.XLOOKUP(A14,CFS_Standalone!A:A,CFS_Standalone!B:B) -> Other Current and Non Current Assets | C14: =_xlfn.XLOOKUP(A14,CFS_Standalone!A:A,CFS_Standalone!C:C) -> 30518
A15: (Increase)/ Decrease in other non current financial asset | B15: Adjustments for other financial assets, non-current | C15: 30452
A16: (Increase)/ Decrease Current Tax Asset | B16: Other Current and Non Current Assets | C16: 30518
A17: (Increase)/ Decrease in other current asset | B17: =_xlfn.XLOOKUP(A17,CFS_Standalone!A:A,CFS_Standalone!B:B) -> Other Current and Non Current Assets | C17: =_xlfn.XLOOKUP(A17,CFS_Standalone!A:A,CFS_Standalone!C:C) -> 30518
A18: (Increase)/ Decrease in other current Financial asset | B18: =_xlfn.XLOOKUP(A18,CFS_Standalone!A:A,CFS_Standalone!B:B) -> Adjustments for other financial assets, current | C18: =_xlfn.XLOOKUP(A18,CFS_Standalone!A:A,CFS_Standalone!C:C) -> 30451
A19: Increase/ (Decrease) in Trade payables | B19: =_xlfn.XLOOKUP(A19,CFS_Standalone!A:A,CFS_Standalone!B:B) -> Trade Payables And Others | C19: =_xlfn.XLOOKUP(A19,CFS_Standalone!A:A,CFS_Standalone!C:C) -> 30675
A20: Increase/(Decrease) in Provision | B20: =_xlfn.XLOOKUP(A20,CFS_Standalone!A:A,CFS_Standalone!B:B) -> Provisions | C20: =_xlfn.XLOOKUP(A20,CFS_Standalone!A:A,CFS_Standalone!C:C) -> 30627
A21: Increase/(Decrease) in other current Liabilities and Provision for exps | B21: Other Current and Non Current Liabilities | C21: 30519
A22: Cash generated from operations | B22: =_xlfn.XLOOKUP(A22,CFS_Standalone!A:A,CFS_Standalone!B:B) -> Cash Generated From Operations | C22: =_xlfn.XLOOKUP(A22,CFS_Standalone!A:A,CFS_Standalone!C:C) -> 30372
A23: Income Taxes paid | B23: =_xlfn.XLOOKUP(A23,CFS_Standalone!A:A,CFS_Standalone!B:B) -> Income Tax Paid | C23: =_xlfn.XLOOKUP(A23,CFS_Standalone!A:A,CFS_Standalone!C:C) -> 30422
A24: Net cash inflow/(outflow) from operating activities | B24: =_xlfn.XLOOKUP(A24,CFS_Standalone!A:A,CFS_Standalone!B:B) -> Net Cash Flow From Operating Activities | C24: =_xlfn.XLOOKUP(A24,CFS_Standalone!A:A,CFS_Standalone!C:C) -> 17538
A25: Cash flow from investing activities | B25: =_xlfn.XLOOKUP(A25,CFS_Standalone!A:A,CFS_Standalone!B:B) -> Lable
A26: Purchase / Sales of non-current investments | B26: Purchase Of Investments | C26: 17557
A27: Purchase / Sales of current investments | B27: Purchase Of Investments | C27: 17557
A28: Purchase of Assets | B28: Purchase Of Fixed Assets (Tangible / Intangible) | C28: 17556
A29: Net cash outflow from investing activities | B29: =_xlfn.XLOOKUP(A29,CFS_Standalone!A:A,CFS_Standalone!B:B) -> Net Cash Flow From Investing Activities | C29: =_xlfn.XLOOKUP(A29,CFS_Standalone!A:A,CFS_Standalone!C:C) -> 17537
A30: Cash Flow from Financing activities | B30: =_xlfn.XLOOKUP(A30,CFS_Standalone!A:A,CFS_Standalone!B:B) -> Lable
A31: lncrease/(Decrease) in Short term borrowings | B31: Proceeds From Short Term Borrowings | C31: 17555
A32: lncrease/(Decrease) in Long term borrowings | B32: Proceeds From Long Term Borrowings | C32: 17554
A33: Finance Cost paid | B33: =_xlfn.XLOOKUP(A33,CFS_Standalone!A:A,CFS_Standalone!B:B) -> Interest Paid | C33: =_xlfn.XLOOKUP(A33,CFS_Standalone!A:A,CFS_Standalone!C:C) -> 30484
A34: Interest Income | B34: Others-Financing Activities | C34: 17543
A35: Loans and advances & others | B35: =_xlfn.XLOOKUP(A35,CFS_Standalone!A:A,CFS_Standalone!B:B) -> Others-Financing Activities | C35: =_xlfn.XLOOKUP(A35,CFS_Standalone!A:A,CFS_Standalone!C:C) -> 17543
A36: Proceeds from Short Term Borrowings | B36: Proceeds From Short Term Borrowings | C36: 17555
A37: Net Adjustment in reserve & surplus for the year | B37: =_xlfn.XLOOKUP(A37,CFS_Standalone!A:A,CFS_Standalone!B:B) -> Transfer On Amalgamation | C37: =_xlfn.XLOOKUP(A37,CFS_Standalone!A:A,CFS_Standalone!C:C) -> 17566
A38: Net cash inflow/(outflow) from Financing activities | B38: =_xlfn.XLOOKUP(A38,CFS_Standalone!A:A,CFS_Standalone!B:B) -> Net Cash Flow From Financing Activities | C38: =_xlfn.XLOOKUP(A38,CFS_Standalone!A:A,CFS_Standalone!C:C) -> 17536
A39: Net Increase/(Decrease) in Cash and Cash Equivalents | B39: =_xlfn.XLOOKUP(A39,CFS_Standalone!A:A,CFS_Standalone!B:B) -> Net increase (decrease) in cash and cash equivalents before effect of exchange rate changes | C39: =_xlfn.XLOOKUP(A39,CFS_Standalone!A:A,CFS_Standalone!C:C) -> 30458
A40: Cash and cash equivalents at the beginning of the financial year | B40: =_xlfn.XLOOKUP(A40,CFS_Standalone!A:A,CFS_Standalone!B:B) -> Cash and Cash Equivalents at the Beginning of the Year | C40: =_xlfn.XLOOKUP(A40,CFS_Standalone!A:A,CFS_Standalone!C:C) -> 17519
A41: Cash and cash equivalents at the end of the financial year | B41: =_xlfn.XLOOKUP(A41,CFS_Standalone!A:A,CFS_Standalone!B:B) -> Cash and Cash Equivalents at the End of the Year | C41: =_xlfn.XLOOKUP(A41,CFS_Standalone!A:A,CFS_Standalone!C:C) -> 30371

Sheet SR_Standalone
A1: Particulars | B1: Cogencis Field | C1: Field id

Sheet SR_Consolidated
A1: Particulars | B1: Cogencis Field | C1: Field id
