Workbook

Sheet P&L_Standalone
A1: Particulars | B1: Cogencis Field | C1: Field id
A2: Income | D2: Heading
A3: Revenue from Operations | B3: Gross Sales/Income from Operations | C3: 256
A4: Other Income | B4: Miscellaneous Income | C4: 265
A5: Total Income | B5: Total Income | C5: 25238
A6: Expenses | D6: Heading
A7: Operating Expenses | B7: Operating Expenses | C7: 276
A8: IT Infrastructure Cost | B8: Operating Expenses | C8: 276
A9: Employee Benefit Expenses | B9: Employee Benefit Expense | C9: 238
A10: Financial Costs | B10: Finance Costs | C10: 246
A11: Depreciation and Amortisation Expenses | B11: Depreciation, Depletion and Amortisation Expense | C11: 232
A12: Other Expenses | D12: Heading
A13: Professional , Consultants & Related Expenses | B13: Other Expenses | C13: 279
A14: General Admin & Other Expenses | B14: Other Expenses | C14: 279
A15: Total Expenses | B15: Total Expenses | C15: 320
A16: Profit before Tax | B16: Profit/(Loss) From Ordinary Activities before Tax | C16: 296
A17: Tax Expense | D17: Heading
A18: Income Tax | B18: Tax Expense | C18: 318
A19: Deferred Tax charge | B19: Deferred Tax | C19: 231
A20: Total Tax Liability | D20: Calculated Field
A21: Profit for the period | B21: Net Profit/(Loss) for the Period | C21: 269
A22: Other comprehensive Income | D22: Heading
A23: Items that will not be reclassified subsequently to profit or loss | D23: Heading
A24: Remeasurement of the net defined benefit (liability) / asset (net of tax) | B24: Items that will not be reclassified to Profit or Loss | C24: 22293
A25: Items that will be reclassified subsequently to profit or loss | D25: Heading
A26: Exchange differences on Remeasurement of foreign transactions | B26: Items that will be reclassified to Profit or Loss | C26: 22294
A27: Equity instruments through other comprehensive income, net | B27: Items that will be reclassified to Profit or Loss | C27: 22294
A28: Other comprehensive income for the period, net of tax | B28: Other Comprehensive Income | C28: 16484
A29: Total comprehensive income for the period | B29: Total Comprehensive Gain (Loss) For the Year | C29: 20019
A30: Paid-up share capital (Face Value ₹ 2/- each fully paid) | B30: Paid-Up Equity Share Capital | C30: 282
A31: Other Equity | B31: Reserve excluding Revaluation Reserves (as per Balance Sheet of Previous Accounting Year) | C31: 309
A32: Earnings per equity share (Face Value ₹ 2/- each) | D32: Heading
A33: Basic ₹ | B33: Basic EPS | C33: 222
A34: Diluted ₹ | B34: Diluted EPS | C34: 234

Sheet P&L_Consolidated
A1: Particulars | B1: Cogencis Field | C1: Field id
A2: Income | D2: Heading
A3: Revenue from Operations | B3: Gross Sales/Income from Operations | C3: 256
A4: Other Income | B4: Miscellaneous Income | C4: 265
A5: Total Income | B5: Total Income | C5: 25238
A6: Expenses | D6: Heading
A7: Operating Expenses | B7: Operating Expenses | C7: 276
A8: IT Infrastructure Cost | B8: Operating Expenses | C8: 276
A9: Employee Benefit Expenses | B9: Employee Benefit Expense | C9: 238
A10: Financial Costs | B10: Finance Costs | C10: 246
A11: Depreciation and Amortisation Expenses | B11: Depreciation, Depletion and Amortisation Expense | C11: 232
A12: Other Expenses | D12: Heading
A13: Professional , Consultants & Related Expenses | B13: Other Expenses | C13: 279
A14: General Admin & Other Expenses | B14: Other Expenses | C14: 279
A15: Total Expenses | B15: Total Expenses | C15: 320
A16: Profit before Tax | B16: Profit/(Loss) From Ordinary Activities before Tax | C16: 296
A17: Tax Expense | D17: Heading
A18: Income Tax | B18: Tax Expense | C18: 318
A19: Deferred Tax charge | B19: Deferred Tax | C19: 231
A20: Total Tax Liability | D20: Calculated Field
A21: Profit for the period | B21: Net Profit/(Loss) for the Period | C21: 269
A22: Other comprehensive income | D22: Heading
A23: Items that will not be reclassified subsequently to profit or loss | D23: Heading
A24: Remeasurement of the net defined benefit (liability) / asset (net of tax) | B24: Items that will not be reclassified to Profit or Loss | C24: 22293
A25: Items that will be reclassified subsequently to profit or loss | D25: Heading
A26: Exchange differences on translation of foreign operations & Remeasurement of foreign transactions | B26: Items that will be reclassified to Profit or Loss | C26: 22294
A27: Equity instruments through other comprehensive income, net | B27: Items that will be reclassified to Profit or Loss | C27: 22294
A28: Other comprehensive income for the period, net of tax | B28: Other Comprehensive Income | C28: 16484
A29: Total comprehensive income for the period | B29: Total Comprehensive Gain (Loss) For the Year | C29: 20019
A30: Paid-up share capital (Face Value ₹2/- each fully paid) | B30: Paid-Up Equity Share Capital | C30: 282
A31: Other Equity | B31: Reserve excluding Revaluation Reserves (as per Balance Sheet of Previous Accounting Year) | C31: 309
A32: Earnings per equity share (Face Value ₹2/ - each) | D32: Heading
A33: Basic ₹ | B33: Basic EPS | C33: 222
A34: Diluted ₹ | B34: Diluted EPS | C34: 234

Sheet BS_Standalone
A1: Particulars | B1: Cogencis Field | C1: Field id
A2: ASSETS | D2: Heading
A3: Non-Current Assets | D3: Heading
A4: Property, Plant and Equipment | D4: Heading
A5: Tangible Assets | B5: Property, Plant & Equipment | C5: 20222
A6: Intangible Assets | B6: Other Intangible Assets | C6: 20221
A7: Intangible Assets Under Development | B7: Intangible assets under development | C7: 13736
A8: Financial Assets | D8: Heading
A9: Investments | B9: Non-Current Investments | C9: 13748
A10: Others Financials Assets | B10: Other Non-Current Financial Assets | C10: 20216
A11: Deferred tax assets (net) | B11: Deferred Tax Assets (Net) | C11: 13726
A12: Other non-current assets | B12: Other Non-Current Assets | C12: 13753
A13: Total Non-Current Assets | B13: Total Non-Current Assets | C13: 13777
A14: Current Assets | D14: Heading
A15: Financial Assets | D15: Heading
A16: Trade Receivables | B16: Trade Receivables | C16: 13780
A17: Cash & Cash equivalents | B17: Cash And Cash Equivalents | C17: 13722
A18: Other Financial Assets | B18: Other Current Financial Assets | C18: 20231
A19: Current tax assets | B19: Current Tax Assets (Net) | C19: 20228
A20: Other current assets | B20: Other Current Assets | C20: 13750
A21: Total Current Assets | B21: Total Current Assets | C21: 13774
A22: Total Assets | B22: Total Assets | C22: 13771
A23: EQUITY AND LIABILITIES | D23: Heading
A24: Equity | D24: Heading
A25: Equity Share capital | B25: Share Capital | C25: 13765
A26: Other Equity | B26: Reserves And Surplus/Other Equity | C26: 13762
A27: Total Equity | B27: Total Share Holder's Funds | C27: 13773
A28: Liabilities | D28: Heading
A29: Non-Current Liabilities | D29: Heading
A30: Financial liabilities | D30: Heading
A31: Borrowings | B31: Borrowings | C31: 20223
A32: Provisions | B32: Long-Term Provisions | C32: 13743
A33: Total Non-current Liabilities | B33: Total Non-Current Liabilities | C33: 13778
A34: Current Liabilities | D34: Heading
A35: Financial liabilities | D35: Heading
A36: Borrowings | B36: Borrowings | C36: 20209
A37: Trade Payables | B37: Trade Payables | C37: 13779
A38: Other current liabilities | B38: Other liabilities | C38: 26450
A39: Total Current Liabilities | B39: Total Current Liabilities | C39: 13775
A40: Total Equity and Liabilities | B40: TOTAL EQUITY AND LIABILITIES | C40: 13776

Sheet BS_Consolidated
A1: Particulars | B1: Cogencis Field | C1: Field id
A2: ASSETS | D2: =VLOOKUP(A2,BS_Standalone!A:D,4,0) -> Heading
A3: Non-Current Assets | D3: =VLOOKUP(A3,BS_Standalone!A:D,4,0) -> Heading
A4: Property, Plant and Equipment | D4: =VLOOKUP(A4,BS_Standalone!A:D,4,0) -> Heading
A5: Tangible Assets | B5: =VLOOKUP($A5,BS_Standalone!A:D,2,0) -> Property, Plant & Equipment | C5: =VLOOKUP($A5,BS_Standalone!A:D,3,0) -> 20222
A6: Intangible Assets | B6: =VLOOKUP($A6,BS_Standalone!A:D,2,0) -> Other Intangible Assets | C6: =VLOOKUP($A6,BS_Standalone!A:D,3,0) -> 20221
A7: Intangible Assets Under Development | B7: =VLOOKUP($A7,BS_Standalone!A:D,2,0) -> Intangible assets under development | C7: =VLOOKUP($A7,BS_Standalone!A:D,3,0) -> 13736
A8: Financial Assets | D8: =VLOOKUP(A8,BS_Standalone!A:D,4,0) -> Heading
A9: Investments | B9: =VLOOKUP($A9,BS_Standalone!A:D,2,0) -> Non-Current Investments | C9: =VLOOKUP($A9,BS_Standalone!A:D,3,0) -> 13748
A10: Others Financials Assets | B10: =VLOOKUP($A10,BS_Standalone!A:D,2,0) -> Other Non-Current Financial Assets | C10: =VLOOKUP($A10,BS_Standalone!A:D,3,0) -> 20216
A11: Deferred tax assets (net) | B11: =VLOOKUP($A11,BS_Standalone!A:D,2,0) -> Deferred Tax Assets (Net) | C11: =VLOOKUP($A11,BS_Standalone!A:D,3,0) -> 13726
A12: Other non-current assets | B12: =VLOOKUP($A12,BS_Standalone!A:D,2,0) -> Other Non-Current Assets | C12: =VLOOKUP($A12,BS_Standalone!A:D,3,0) -> 13753
A13: Total Non-Current Assets | B13: =VLOOKUP($A13,BS_Standalone!A:D,2,0) -> Total Non-Current Assets | C13: =VLOOKUP($A13,BS_Standalone!A:D,3,0) -> 13777
A14: Current Assets | D14: =VLOOKUP(A14,BS_Standalone!A:D,4,0) -> Heading
A15: Financial Assets | D15: =VLOOKUP(A15,BS_Standalone!A:D,4,0) -> Heading
A16: Trade Receivables | B16: =VLOOKUP($A16,BS_Standalone!A:D,2,0) -> Trade Receivables | C16: =VLOOKUP($A16,BS_Standalone!A:D,3,0) -> 13780
A17: Cash & Cash equivalents | B17: =VLOOKUP($A17,BS_Standalone!A:D,2,0) -> Cash And Cash Equivalents | C17: =VLOOKUP($A17,BS_Standalone!A:D,3,0) -> 13722
A18: Other Financial Assets | B18: =VLOOKUP($A18,BS_Standalone!A:D,2,0) -> Other Current Financial Assets | C18: =VLOOKUP($A18,BS_Standalone!A:D,3,0) -> 20231
A19: Current tax assets | B19: =VLOOKUP($A19,BS_Standalone!A:D,2,0) -> Current Tax Assets (Net) | C19: =VLOOKUP($A19,BS_Standalone!A:D,3,0) -> 20228
A20: Other current assets | B20: =VLOOKUP($A20,BS_Standalone!A:D,2,0) -> Other Current Assets | C20: =VLOOKUP($A20,BS_Standalone!A:D,3,0) -> 13750
A21: Total Current Assets | B21: =VLOOKUP($A21,BS_Standalone!A:D,2,0) -> Total Current Assets | C21: =VLOOKUP($A21,BS_Standalone!A:D,3,0) -> 13774
A22: Total Assets | B22: =VLOOKUP($A22,BS_Standalone!A:D,2,0) -> Total Assets | C22: =VLOOKUP($A22,BS_Standalone!A:D,3,0) -> 13771
A23: EQUITY AND LIABILITIES | D23: =VLOOKUP(A23,BS_Standalone!A:D,4,0) -> Heading
A24: Equity | D24: =VLOOKUP(A24,BS_Standalone!A:D,4,0) -> Heading
A25: Equity Share capital | B25: =VLOOKUP($A25,BS_Standalone!A:D,2,0) -> Share Capital | C25: =VLOOKUP($A25,BS_Standalone!A:D,3,0) -> 13765
A26: Other Equity | B26: =VLOOKUP($A26,BS_Standalone!A:D,2,0) -> Reserves And Surplus/Other Equity | C26: =VLOOKUP($A26,BS_Standalone!A:D,3,0) -> 13762
A27: Total Equity | B27: =VLOOKUP($A27,BS_Standalone!A:D,2,0) -> Total Share Holder's Funds | C27: =VLOOKUP($A27,BS_Standalone!A:D,3,0) -> 13773
A28: Liabilities | D28: =VLOOKUP(A28,BS_Standalone!A:D,4,0) -> Heading
A29: Non-Current Liabilities | D29: =VLOOKUP(A29,BS_Standalone!A:D,4,0) -> Heading
A30: Financial liabilities | D30: =VLOOKUP(A30,BS_Standalone!A:D,4,0) -> Heading
A31: Borrowings | B31: =VLOOKUP($A31,BS_Standalone!A:D,2,0) -> Borrowings | C31: =VLOOKUP($A31,BS_Standalone!A:D,3,0) -> 20223
A32: Provisions | B32: =VLOOKUP($A32,BS_Standalone!A:D,2,0) -> Long-Term Provisions | C32: =VLOOKUP($A32,BS_Standalone!A:D,3,0) -> 13743
A33: Total Non-current Liabilities | B33: =VLOOKUP($A33,BS_Standalone!A:D,2,0) -> Total Non-Current Liabilities | C33: =VLOOKUP($A33,BS_Standalone!A:D,3,0) -> 13778
A34: Current Liabilities | D34: =VLOOKUP(A34,BS_Standalone!A:D,4,0) -> Heading
A35: Financial liabilities | D35: =VLOOKUP(A35,BS_Standalone!A:D,4,0) -> Heading
A36: Borrowings | B36: Borrowings | C36: 20209
A37: Trade Payables | B37: Trade Payables | C37: 13779
A38: Other current liabilities | B38: =VLOOKUP($A38,BS_Standalone!A:D,2,0) -> Other liabilities | C38: =VLOOKUP($A38,BS_Standalone!A:D,3,0) -> 26450
A39: Total Current Liabilities | B39: =VLOOKUP($A39,BS_Standalone!A:D,2,0) -> Total Current Liabilities | C39: =VLOOKUP($A39,BS_Standalone!A:D,3,0) -> 13775
A40: Total Equity and Liabilities | B40: =VLOOKUP($A40,BS_Standalone!A:D,2,0) -> TOTAL EQUITY AND LIABILITIES | C40: =VLOOKUP($A40,BS_Standalone!A:D,3,0) -> 13776

Sheet CFS_Standalone
A1: Particulars | B1: Cogencis Field | C1: Field id
A2: Cash Flow from Operating Activities | D2: Heading
A3: Net Profit/(Loss) before tax | B3: Net Profit Before Tax And Exceptional Item | C3: 17539
A4: Adjustment for: | D4: Heading
A5: Depreciation & Amortisation Expense | B5: Depreciation and Amortisation Expense | C5: 30399
A6: Equity instruments through other comprehensive income | B6: Others-Before Working Capital Changes | C6: 17542
A7: Re-measurement gains/(losses) on employee defined benefit plans | B7: Others-Before Working Capital Changes | C7: 17542
A8: Exchange differences on translation of foreign operations | B8: Foreign Exchange Gain / Loss | C8: 30414
A9: Income Tax | B9: Income Tax Paid | C9: 30422
A10: Other Income | B10: Others-Before Working Capital Changes | C10: 17542
A11: Operating Profit/(Loss) before working capital changes | B11: Operating Profit Before Working Capital Changes | C11: 30511
A12: Adjustment for: | D12: Heading
A13: (Increase)/Decrease in Trade Receivables | B13: Trade And Other Receivables | C13: 30674
A14: (Increase)/Decrease in Other Current Assets | B14: Other Current and Non Current Assets | C14: 30518
A15: Increase/(Decrease) in Current Liabilities | B15: Other Current and Non Current Liabilities | C15: 30519
A16: Cash generated from Operations | B16: Cash Generated From Operations | C16: 30372
A17: Prior Period Items | B17: Income/Expenses Relating To Prior Years | C17: 30450
A18: Net Cash Flow generated / (used in) from Operating Activities | B18: Net Cash Flow From Operating Activities | C18: 17538
A19: Cash Flow from Investing Activities | D19: Heading
A20: (Increase)/Decrease in Fixed Assets | B20: Purchase Of Fixed Assets (Tangible / Intangible) | C20: 17556
A21: (Increase)/Decrease in Non-current Investments | B21: Purchase Of Investments | C21: 17557
A22: (Increase)/Decrease in Fixed Deposits Mutual Funds and other Non current assets | B22: Fixed Deposits | C22: 30412
A23: Increase/(Decrease) in Non-current Liabilities | B23: Others-Investing Activities | C23: 17545
A24: Other Income Received | B24: Others-Investing Activities | C24: 17545
A25: Net Cash Flow generated / (used In) from Investing Activities | B25: Net Cash Flow From Investing Activities | C25: 17537
A26: Cash Flow from Financing Activities | D26: Heading
A27: Increase/(Decrease) in Share Capital | B27: Proceeds From Issue Of Equity Shares (Inclu Share Premium) | C27: 17553
A28: Increase/(Decrease) in Other Equity | B28: Proceeds From Issue Of Equity Shares (Inclu Share Premium) | C28: 17553
A29: Dividend | B29: Dividend Paid | C29: 17528
A30: Net Cash Flow generated / (used in) from Financing Activities | B30: Net Cash Flow From Financing Activities | C30: 17536
A31: Net increase / (decrease) in cash and cash equivalents | B31: Net Increase in Cash and Cash Equivalents | C31: 17541
A32: Cash & Cash equivalents (Opening Balance) | B32: Cash and Cash Equivalents at the Beginning of the Year | C32: 17519
A33: Cash & Cash equivalents (Closing Balance) | B33: Cash and Cash Equivalents at the End of the Year | C33: 30371

Sheet CFS_Consolidated
A1: Particulars | B1: Cogencis Field | C1: Field id
A2: Cash Flow from Operating Activities | D2: Heading
A3: Net Profit/(Loss) before tax | B3: Net Profit Before Tax And Exceptional Item | C3: 17539
A4: Adjustment for: | D4: Heading
A5: Depreciation & Amortisation Expense | B5: Depreciation and Amortisation Expense | C5: 30399
A6: Equity instruments through other comprehensive income | B6: Others-Before Working Capital Changes | C6: 17542
A7: Re-measurement gains/(losses) on employee defined benefit plans | B7: Others-Before Working Capital Changes | C7: 17542
A8: Exchange differences on translation of foreign operations & Remeasurement of foreign transactions | B8: Foreign Exchange Gain / Loss | C8: 30414
A9: Income Tax | B9: Income Tax Paid | C9: 30422
A10: Other Income | B10: Others-Before Working Capital Changes | C10: 17542
A11: Operating Profit/(Loss) before working capital changes | B11: Operating Profit Before Working Capital Changes | C11: 30511
A12: Adjustment for: | D12: Heading
A13: (Increase)/Decrease in Trade Receivables | B13: Trade And Other Receivables | C13: 30674
A14: (Increase)/Decrease in Other Current Assets | B14: Other Current and Non Current Assets | C14: 30518
A15: Increase/(Decrease) in Current Liabilities | B15: Other Current and Non Current Liabilities | C15: 30519
A16: Cash generated from Operations | B16: Cash Generated From Operations | C16: 30372
A17: Prior Period Items | B17: Income/Expenses Relating To Prior Years | C17: 30450
A18: Net Cash Flow generated / (used in) from Operating Activities | B18: Net Cash Flow From Operating Activities | C18: 17538
A19: Cash Flow from Investing Activities | D19: Heading
A20: (Increase)/Decrease in Fixed Assets | B20: Purchase Of Fixed Assets (Tangible / Intangible) | C20: 17556
A21: (Increase)/Decrease in Non-current Investments | B21: Purchase Of Investments | C21: 17557
A22: (Increase)/Decrease in Fixed Deposits Mutual Funds and other Non current assets | B22: Fixed Deposits | C22: 30412
A23: Increase/(Decrease) In Non-current Liabilities | B23: Others-Investing Activities | C23: 17545
A24: Other Income Received | B24: Others-Investing Activities | C24: 17545
A25: Net Cash Flow generated / (used in) from Investing Activities | B25: Net Cash Flow From Investing Activities | C25: 17537
A26: Cash Flow from Financing Activities | D26: Heading
A27: Increase/(Decrease) in Share Capital | B27: Proceeds From Issue Of Equity Shares (Inclu Share Premium) | C27: 17553
A28: Increase/(Decrease) in Other Equity | B28: Proceeds From Issue Of Equity Shares (Inclu Share Premium) | C28: 17553
A29: Effect of exchange differences on transiation of foreign currency cash and cash equivalents | B29: Others-Financing Activities | C29: 17543
A30: Dividend | B30: Dividend Paid | C30: 17528
A31: Net Cash Flow generated / (used in) from Financing Activities | B31: Net Cash Flow From Financing Activities | C31: 17536
A32: Net increase / (decrease) in cash and cash equivalents | B32: Net Increase in Cash and Cash Equivalents | C32: 17541
A33: Cash & Cash equivalents (Opening Balance) | B33: Cash and Cash Equivalents at the Beginning of the Year | C33: 17519
A34: Cash & Cash equivalents (Closing Balance) | B34: Cash and Cash Equivalents at the End of the Year | C34: 30371

Sheet SR_Standalone
A1: Particulars | B1: Cogencis Field | C1: Field id

Sheet SR_Consolidated
A1: Particulars | B1: Cogencis Field | C1: Field id
