Workbook

Sheet P&L_Standalone
A1: Particulars | B1: Cogencis Field | C1: Field id
A2: Revenue from Operations | B2: Gross Sales/Income from Operations | C2: 256
A3: Other Income | B3: Miscellaneous Income | C3: 265
A4: Total Revenue | B4: Total Income | C4: 25238
A5: Expenses | B5: Lable
A6: Employee benefits expense | B6: Employee Benefit Expense | C6: 238
A7: Sub-Contracting & Technical Fee | B7: Operating Expenses | C7: 276
A8: Finance Costs | B8: Finance Costs | C8: 246
A9: Depreciation and amortisation expense | B9: Depreciation, Depletion and Amortisation Expense | C9: 232
A10: Other expenses | B10: Other Expenses | C10: 279
A11: Total Expenses | B11: Total Expenses | C11: 320
A12: Profit / (Loss) before exceptional Items and tax | B12: Profit/(Loss) from Ordinary Activities after Finance Costs but before Exceptional Items | C12: 294
A13: Exceptional Items | B13: Other Exceptional Items | C13: 278
A14: Profit / (Loss) before Tax | B14: Profit/(Loss) From Ordinary Activities before Tax | C14: 296
A15: Tax Expenses | B15: Lable
A16: Current Tax | B16: Tax Expense | C16: 318
A17: Deferred Tax | B17: Deferred Tax | C17: 231
A18: Profit (Loss) for the period from continuing operations | B18: Profit/(Loss) for the Period from Continuing Operations | C18: 20017
A19: Profitloss) from discontinuing operations | B19: Profit/(Loss) from Discontinuing Operations | C19: 20016
A20: Tax expense of discontinuing operations | B20: Tax Expense of Discontinuing Operations | C20: 20018
A21: Profit/(Loss) from Discontinuing operations (after tax) | B21: Net Profit From Discontinuing Operations (After Tax) | C21: 20015
A22: Profit/(Loss) for the period | B22: Net Profit/(Loss) for the Period | C22: 269
A23: Other Comperhensive income/(Expense) | B23: Other Comprehensive Income | C23: 16484 | D23: Bifurcation not Give
A24: Total Comprehensive Income (Comprising Profit (Loss) and Other Comprehensive Income for the period) | B24: Total Comprehensive Gain (Loss) For the Year | C24: 20019
A25: Paid-up Equity Share Capital | B25: Paid-Up Equity Share Capital | C25: 282
A26: Face Value ( In Rs. ) | B26: Face Value | C26: 245
A27: Reserve excluding Revaluation Reserves as per balance sheet of previous accounting year | B27: Reserve excluding Revaluation Reserves (as per Balance Sheet of Previous Accounting Year) | C27: 309
A28: Earning Per Share (Rs)* (Not annualised ) | B28: Lable
A29: Basic EPS (in Rs ) | B29: Basic EPS | C29: 222
A30: Diluted EPS (in Rs.) | B30: Diluted EPS | C30: 234
A31: Number of shares used in computing Earnings per Equity Shares (taken face value of Re.1/-) | B31: Lable | D31: Ignore This Field
A32: Basic | B32: Basic EPS | C32: 222 | D32: Ignore This Field
A33: Diluted | B33: Diluted EPS | C33: 234 | D33: Ignore This Field

Sheet P&L_Consolidated
A1: Particulars | B1: Cogencis Field | C1: Field id
A2: Revenue from Operations | B2: Gross Sales/Income from Operations | C2: 256
A3: Other Income | B3: Miscellaneous Income | C3: 265
A4: Total Revenue | B4: Total Income | C4: 25238
A5: Expenses
A6: Purchase of Stock-in-trade | B6: Purchase of Stock-in-Trade | C6: 307
A7: Change in Inventories of Stock-in-trade | B7: Changes in Inventories of Finished Goods, Work-In-Progress and Stock-In-Trade | C7: 227
A8: Employee benefits expense | B8: Employee Benefit Expense | C8: 238
A9: Sub-Contracting & Technical Fee | B9: Operating Expenses | C9: 276
A10: Finance Costs | B10: Finance Costs | C10: 246
A11: Depreciation and amortisation expense | B11: Depreciation, Depletion and Amortisation Expense | C11: 232
A12: Other expenses | B12: Other Expenses | C12: 279
A13: Total Expenses | B13: Total Expenses | C13: 320
A14: Profit Before Share of Profit / (Loss) of Associates, Exceptional Item and Tax | B14: Profit/(Loss) from ordinary activities after finance costs but before exceptional items | C14: 294
A15: Share of Profit / (Loss) of Associates | B15: Share of Profit/(loss) of associates and Joint Ventures before ebt | C15: 25236
A16: Profit Before Exceptional Item and Tax | B16: Profit/(Loss) from ordinary activities after finance costs but before exceptional items | C16: 294
A17: Exceptional Items | B17: Other Exceptional Items | C17: 278
A18: Profit /(Loss) before Tax | B18: Profit/(Loss) From Ordinary Activities before Tax | C18: 296
A19: Tax Expenses
A20: Current | B20: Tax Expense | C20: 318
A21: Deferred | B21: Deferred Tax | C21: 231
A22: Profit (Loss) for the period from continuing operations | B22: Profit/(Loss) for the Period from Continuing Operations | C22: 20017
A23: Profit/(loss) from discontinuing operations | B23: Profit/(Loss) from Discontinuing Operations | C23: 20016
A24: Tax expense of discontinuing operations | B24: Tax Expense of Discontinuing Operations | C24: 20018
A25: Profit/(loss) from Discontinuing operations (after tax) | B25: Net Profit From Discontinuing Operations (After Tax) | C25: 20015
A26: Profit (Loss) for the period | B26: Net Profit/(Loss) for the Period | C26: 269
A27: Other Comperhensive Income/(Expense) | B27: Other Comprehensive Income | C27: 16484 | D27: Bifurcation not Give
A28: Total Comprehensive Income (Comprising Profit (Loss) and Other Comprehensive Income for the period) | B28: Total Comprehensive Gain (Loss) For the Year | C28: 20019
A29: Paid-up Equity Share Capital | B29: Paid-Up Equity Share Capital | C29: 282
A30: Face Value ( In Rs. ) | B30: Face Value | C30: 245
A31: Reserve excluding Revaluation Reserves as per balance sheet of previous accounting year | B31: Reserve excluding Revaluation Reserves (as per Balance Sheet of Previous Accounting Year) | C31: 309
A32: Earning Per Share (Rs)* ( Not annualised )
A33: Basic EPS (in Rs.) | B33: Basic EPS | C33: 222
A34: Diluted EPS (in Rs.) | B34: Diluted EPS | C34: 234
A35: Number of shares used in computing earnings per equity shares | D35: Ignore This Field
A36: Basic | B36: Basic EPS | C36: 222 | D36: Ignore This Field
A37: Diluted | B37: Diluted EPS | C37: 234 | D37: Ignore This Field

Sheet BS_Standalone
A1: Particulars | B1: Cogencis Field | C1: Field id
A2: ASSETS | B2: Lable
A3: Non-current assets | B3: Lable
A4: Property, Plant and Equipment | B4: Property, Plant & Equipment | C4: 20222
A5: Intangible Assets | B5: Other Intangible Assets | C5: 20221
A6: Investment Property | B6: Investment Property | C6: 25736
A7: Financial assets | B7: Lable
A8: Investments | B8: Non-Current Investments | C8: 13748
A9: Loans and advances | B9: Loans Non-Current | C9: 20217
A10: Others | B10: Other Non-Current Financial Assets | C10: 20216
A11: Deferred tax assets (Net) | B11: Deferred Tax Assets (Net) | C11: 13726
A12: Non-Current Tax Assets (Net) | B12: Income Tax assets (net) | C12: 20215
A13: Current assets | B13: Lable
A14: Financial assets | B14: Lable
A15: Trade Receivables | B15: Trade Receivables | C15: 13780
A16: Cash and cash equivalents | B16: Cash And Cash Equivalents | C16: 13722
A17: Other balances with banks | B17: Bank balance other than cash and cash equivalents | C17: 29788
A18: Loans and advances | B18: Loans, Current | C18: 20230
A19: Other Current Assets | B19: Other Current Assets | C19: 13750
A20: TOTAL | B20: Total Assets | C20: 13771
A21: EQUITY AND LIABILITIES | B21: Lable
A22: Equity | B22: Lable
A23: Equity Share Capital | B23: Share Capital | C23: 13765
A24: Other Equity | B24: Reserves And Surplus/Other Equity | C24: 13762
A25: Non-current liabilities | B25: Lable
A26: Financial liabilities | B26: Lable
A27: Other Financial Liabilities | B27: Other Non Current Financial Liabilities | C27: 20226
A28: Non-Current Provisions | B28: Long-Term Provisions | C28: 13743
A29: Current liabilities | B29: Lable
A30: Financial liabilities | B30: Lable
A31: Trade payables
A32: Total outstanding dues of Micro, Small & Medium Enterprise | B32: Trade Payables | C32: 13779
A33: Total outstanding dues of creditors other than Micro, Small & Medium Enterprise | B33: Trade Payables | C33: 13779
A34: Other Financial Liabilities | B34: Other Current Financial Liabilities | C34: 20214
A35: Current Provisions | B35: Short-Term Provisions | C35: 13767
A36: Other Current Liabilities | B36: Other liabilities | C36: 26450
A37: TOTAL | B37: Total Equity And Liabilities | C37: 13776

Sheet BS_Consolidated
A1: Particulars | B1: Cogencis Field | C1: Field id
A2: ASSETS | B2: =_xlfn.XLOOKUP(A2,BS_Standalone!A:A,BS_Standalone!B:B) -> Lable
A3: Non-current assets | B3: =_xlfn.XLOOKUP(A3,BS_Standalone!A:A,BS_Standalone!B:B) -> Lable
A4: Property, Plant and Equipment | B4: =_xlfn.XLOOKUP(A4,BS_Standalone!A:A,BS_Standalone!B:B) -> Property, Plant & Equipment | C4: =_xlfn.XLOOKUP(A4,BS_Standalone!A:A,BS_Standalone!C:C) -> 20222
A5: Intangible Assets | B5: =_xlfn.XLOOKUP(A5,BS_Standalone!A:A,BS_Standalone!B:B) -> Other Intangible Assets | C5: =_xlfn.XLOOKUP(A5,BS_Standalone!A:A,BS_Standalone!C:C) -> 20221
A6: Goodwill | B6: Goodwill On Consolidation | C6: 13734
A7: Investment Property | B7: =_xlfn.XLOOKUP(A7,BS_Standalone!A:A,BS_Standalone!B:B) -> Investment Property | C7: =_xlfn.XLOOKUP(A7,BS_Standalone!A:A,BS_Standalone!C:C) -> 25736
A8: Financial assets | B8: =_xlfn.XLOOKUP(A8,BS_Standalone!A:A,BS_Standalone!B:B) -> Lable
A9: Investments | B9: =_xlfn.XLOOKUP(A9,BS_Standalone!A:A,BS_Standalone!B:B) -> Non-Current Investments | C9: =_xlfn.XLOOKUP(A9,BS_Standalone!A:A,BS_Standalone!C:C) -> 13748
A10: Loans and advances | B10: =_xlfn.XLOOKUP(A10,BS_Standalone!A:A,BS_Standalone!B:B) -> Loans Non-Current | C10: =_xlfn.XLOOKUP(A10,BS_Standalone!A:A,BS_Standalone!C:C) -> 20217
A11: Others | B11: =_xlfn.XLOOKUP(A11,BS_Standalone!A:A,BS_Standalone!B:B) -> Other Non-Current Financial Assets | C11: =_xlfn.XLOOKUP(A11,BS_Standalone!A:A,BS_Standalone!C:C) -> 20216
A12: Deferred tax assets (Net) | B12: =_xlfn.XLOOKUP(A12,BS_Standalone!A:A,BS_Standalone!B:B) -> Deferred Tax Assets (Net) | C12: =_xlfn.XLOOKUP(A12,BS_Standalone!A:A,BS_Standalone!C:C) -> 13726
A13: Non-Current Tax Assets (Net) | B13: =_xlfn.XLOOKUP(A13,BS_Standalone!A:A,BS_Standalone!B:B) -> Income Tax assets (net) | C13: =_xlfn.XLOOKUP(A13,BS_Standalone!A:A,BS_Standalone!C:C) -> 20215
A14: Current assets | B14: =_xlfn.XLOOKUP(A14,BS_Standalone!A:A,BS_Standalone!B:B) -> Lable
A15: Inventories | B15: Inventories | C15: 13737
A16: Trade Receivables | B16: =_xlfn.XLOOKUP(A16,BS_Standalone!A:A,BS_Standalone!B:B) -> Trade Receivables | C16: =_xlfn.XLOOKUP(A16,BS_Standalone!A:A,BS_Standalone!C:C) -> 13780
A17: Cash and cash equivalents | B17: =_xlfn.XLOOKUP(A17,BS_Standalone!A:A,BS_Standalone!B:B) -> Cash And Cash Equivalents | C17: =_xlfn.XLOOKUP(A17,BS_Standalone!A:A,BS_Standalone!C:C) -> 13722
A18: Other balances with banks | B18: =_xlfn.XLOOKUP(A18,BS_Standalone!A:A,BS_Standalone!B:B) -> Bank balance other than cash and cash equivalents | C18: =_xlfn.XLOOKUP(A18,BS_Standalone!A:A,BS_Standalone!C:C) -> 29788
A19: Loans and advances | B19: Loans, Current | C19: 20230
A20: Other Current Assets | B20: =_xlfn.XLOOKUP(A20,BS_Standalone!A:A,BS_Standalone!B:B) -> Other Current Assets | C20: =_xlfn.XLOOKUP(A20,BS_Standalone!A:A,BS_Standalone!C:C) -> 13750
A21: TOTAL | B21: =_xlfn.XLOOKUP(A21,BS_Standalone!A:A,BS_Standalone!B:B) -> Total Assets | C21: =_xlfn.XLOOKUP(A21,BS_Standalone!A:A,BS_Standalone!C:C) -> 13771
A22: EQUITY AND LIABILITIES | B22: =_xlfn.XLOOKUP(A22,BS_Standalone!A:A,BS_Standalone!B:B) -> Lable
A23: Equity | B23: =_xlfn.XLOOKUP(A23,BS_Standalone!A:A,BS_Standalone!B:B) -> Lable
A24: Equity Share capital | B24: =_xlfn.XLOOKUP(A24,BS_Standalone!A:A,BS_Standalone!B:B) -> Share Capital | C24: =_xlfn.XLOOKUP(A24,BS_Standalone!A:A,BS_Standalone!C:C) -> 13765
A25: Other Equity | B25: =_xlfn.XLOOKUP(A25,BS_Standalone!A:A,BS_Standalone!B:B) -> Reserves And Surplus/Other Equity | C25: =_xlfn.XLOOKUP(A25,BS_Standalone!A:A,BS_Standalone!C:C) -> 13762
A26: Non Controlling Interest | B26: Minority Interest | C26: 13744
A27: Non-current liabilities | B27: =_xlfn.XLOOKUP(A27,BS_Standalone!A:A,BS_Standalone!B:B) -> Lable
A28: Financial liabilities | B28: =_xlfn.XLOOKUP(A28,BS_Standalone!A:A,BS_Standalone!B:B) -> Lable
A29: Other Financial Liabilities | B29: =_xlfn.XLOOKUP(A29,BS_Standalone!A:A,BS_Standalone!B:B) -> Other Non Current Financial Liabilities | C29: =_xlfn.XLOOKUP(A29,BS_Standalone!A:A,BS_Standalone!C:C) -> 20226
A30: Non-Current Provisions | B30: =_xlfn.XLOOKUP(A30,BS_Standalone!A:A,BS_Standalone!B:B) -> Long-Term Provisions | C30: =_xlfn.XLOOKUP(A30,BS_Standalone!A:A,BS_Standalone!C:C) -> 13743
A31: Current liabilities | B31: Lable
A32: Financial liabilities | B32: =_xlfn.XLOOKUP(A32,BS_Standalone!A:A,BS_Standalone!B:B) -> Lable
A33: Trade payables
A34: Total outstanding dues of Micro, Small & Medium Enterprise | B34: =_xlfn.XLOOKUP(A34,BS_Standalone!A:A,BS_Standalone!B:B) -> Trade Payables | C34: =_xlfn.XLOOKUP(A34,BS_Standalone!A:A,BS_Standalone!C:C) -> 13779
A35: Total outstanding dues of creditors other than Micro, Small & Medium Enterprise | B35: =_xlfn.XLOOKUP(A35,BS_Standalone!A:A,BS_Standalone!B:B) -> Trade Payables | C35: =_xlfn.XLOOKUP(A35,BS_Standalone!A:A,BS_Standalone!C:C) -> 13779
A36: Other Financial Liabilities | B36: Other Current Financial Liabilities | C36: 20214
A37: Current Provisions | B37: Short-Term Provisions | C37: 13767
A38: Other Current Liabilities | B38: Total Current Liabilities | C38: 13775
A39: TOTAL | B39: Total Equity And Liabilities | C39: 13776

Sheet CFS_Standalone
A1: Particulars | B1: Cogencis Field | C1: Field id
A2: CASH FLOW FROM OPERATING ACTIVITIES | B2: Lable
A3: Net Profit Before Tax | B3: Net Profit Before Tax And Exceptional Item | C3: 17539
A4: Adjustments for | B4: Lable
A5: Depreciation and amortisation | B5: Depreciation and Amortisation Expense | C5: 30399
A6: Interest income | B6: Interest Income | C6: 30481
A7: Finance costs | B7: Interest Expense | C7: 30479
A8: Working capital adjustments | B8: Lable
A9: (Increase)/Decrease in Trade Receivables | B9: Trade And Other Receivables | C9: 30674
A10: (Increase)/Decrease in Loans and Advances | B10: Loans And Advances | C10: 30497
A11: (Increase)/Decrease in Other Assets | B11: Other Current and Non Current Assets | C11: 30518
A12: Increase/(Decrease) in Trade Payables | B12: Trade Payables And Others | C12: 30675
A13: Increase/(Decrease) in Provisions | B13: Provisions | C13: 30627
A14: Increase/(Decrease) in Current Liabilities | B14: Other Current and Non Current Liabilities | C14: 30519
A15: Cash Generated from Operations | B15: Cash Generated From Operations | C15: 30372
A16: Income Tax Paid | B16: Income Tax Paid | C16: 30422
A17: NET CASH GENERATED/(USED IN) BY OPERATING ACTIVITIES | B17: Net Cash Flow From Operating Activities | C17: 17538
A18: CASH FLOW FROM INVESTING ACTIVITIES | B18: Lable
A19: Purchase of property, plant and equipment | B19: Purchase Of Fixed Assets (Tangible / Intangible) | C19: 17556
A20: Interest Income | B20: Interest Received | C20: 30485
A21: NET CASH GENERATED/(USED IN) BY INVESTING ACTIVITIES | B21: Net Cash Flow From Investing Activities | C21: 17537
A22: CASH FLOW FROM FINANCING ACTIVITIES | B22: Lable
A23: Finance costs | B23: Interest Paid | C23: 30484
A24: NET CASH GENERATED/(USED IN) BY FINANCING ACTIVITIES | B24: Net Cash Flow From Financing Activities | C24: 17536
A25: NET INCREASE/(DECREASE) IN CASH AND CASH EQUIVALENTS | B25: Net increase (decrease) in cash and cash equivalents before effect of exchange rate changes | C25: 30458
A26: Cash and cash equivalents at the beginning of the year | B26: Cash and Cash Equivalents at the Beginning of the Year | C26: 17519
A27: CASH AND CASH EQUIVALENTS AT THE END OF THE YEAR | B27: Cash and Cash Equivalents at the End of the Year | C27: 30371

Sheet CFS_Consolidated
A1: Particulars | B1: Cogencis Field | C1: Field id
A2: CASH FLOW FROM OPERATING ACTIVITIES | B2: =_xlfn.XLOOKUP(A2,CFS_Standalone!A:A,CFS_Standalone!B:B) -> Lable
A3: Net Profit Before Tax | B3: =_xlfn.XLOOKUP(A3,CFS_Standalone!A:A,CFS_Standalone!B:B) -> Net Profit Before Tax And Exceptional Item | C3: =_xlfn.XLOOKUP(A3,CFS_Standalone!A:A,CFS_Standalone!C:C) -> 17539
A4: Adjustments for | B4: =_xlfn.XLOOKUP(A4,CFS_Standalone!A:A,CFS_Standalone!B:B) -> Lable
A5: Depreciation and amortisation | B5: =_xlfn.XLOOKUP(A5,CFS_Standalone!A:A,CFS_Standalone!B:B) -> Depreciation and Amortisation Expense | C5: =_xlfn.XLOOKUP(A5,CFS_Standalone!A:A,CFS_Standalone!C:C) -> 30399
A6: Associates Loss/(Profit) | B6: Others-Before Working Capital Changes | C6: 17542
A7: Interest income | B7: Interest Income | C7: 30481
A8: Finance costs | B8: Interest Expense | C8: 30479
A9: Working capital adjustments | B9: =_xlfn.XLOOKUP(A9,CFS_Standalone!A:A,CFS_Standalone!B:B) -> Lable
A10: (Increase)/Decrease in Trade Receivables | B10: =_xlfn.XLOOKUP(A10,CFS_Standalone!A:A,CFS_Standalone!B:B) -> Trade And Other Receivables | C10: =_xlfn.XLOOKUP(A10,CFS_Standalone!A:A,CFS_Standalone!C:C) -> 30674
A11: (Increase)/Decrease in Loans and Advances | B11: =_xlfn.XLOOKUP(A11,CFS_Standalone!A:A,CFS_Standalone!B:B) -> Loans And Advances | C11: =_xlfn.XLOOKUP(A11,CFS_Standalone!A:A,CFS_Standalone!C:C) -> 30497
A12: (Increase)/Decrease in Other Assets | B12: =_xlfn.XLOOKUP(A12,CFS_Standalone!A:A,CFS_Standalone!B:B) -> Other Current and Non Current Assets | C12: =_xlfn.XLOOKUP(A12,CFS_Standalone!A:A,CFS_Standalone!C:C) -> 30518
A13: (Increase)/Decrease in Inventories | B13: Inventories | C13: 30487
A14: Increase/(Decrease) in Trade Payables | B14: =_xlfn.XLOOKUP(A14,CFS_Standalone!A:A,CFS_Standalone!B:B) -> Trade Payables And Others | C14: =_xlfn.XLOOKUP(A14,CFS_Standalone!A:A,CFS_Standalone!C:C) -> 30675
A15: Increase/(Decrease) in Provisions | B15: =_xlfn.XLOOKUP(A15,CFS_Standalone!A:A,CFS_Standalone!B:B) -> Provisions | C15: =_xlfn.XLOOKUP(A15,CFS_Standalone!A:A,CFS_Standalone!C:C) -> 30627
A16: Increase/(Decrease) in Current Liabilities | B16: =_xlfn.XLOOKUP(A16,CFS_Standalone!A:A,CFS_Standalone!B:B) -> Other Current and Non Current Liabilities | C16: =_xlfn.XLOOKUP(A16,CFS_Standalone!A:A,CFS_Standalone!C:C) -> 30519
A17: Cash Generated from Operations | B17: =_xlfn.XLOOKUP(A17,CFS_Standalone!A:A,CFS_Standalone!B:B) -> Cash Generated From Operations | C17: =_xlfn.XLOOKUP(A17,CFS_Standalone!A:A,CFS_Standalone!C:C) -> 30372
A18: Income Tax Paid | B18: =_xlfn.XLOOKUP(A18,CFS_Standalone!A:A,CFS_Standalone!B:B) -> Income Tax Paid | C18: =_xlfn.XLOOKUP(A18,CFS_Standalone!A:A,CFS_Standalone!C:C) -> 30422
A19: NET CASH GENERATED/(USED IN) BY OPERATING ACTIVITIES | B19: =_xlfn.XLOOKUP(A19,CFS_Standalone!A:A,CFS_Standalone!B:B) -> Net Cash Flow From Operating Activities | C19: =_xlfn.XLOOKUP(A19,CFS_Standalone!A:A,CFS_Standalone!C:C) -> 17538
A20: CASH FLOW FROM INVESTING ACTIVITIES | B20: =_xlfn.XLOOKUP(A20,CFS_Standalone!A:A,CFS_Standalone!B:B) -> Lable
A21: Purchase of property, plant and equipments | B21: Purchase Of Fixed Assets (Tangible / Intangible) | C21: 17556
A22: Interest Income | B22: Interest Received | C22: 30485
A23: NET CASH GENERATED/(USED IN) BY INVESTING ACTIVITIES | B23: Net Cash Flow From Investing Activities | C23: 17537
A24: CASH FLOW FROM FINANCING ACTIVITIES | B24: =_xlfn.XLOOKUP(A24,CFS_Standalone!A:A,CFS_Standalone!B:B) -> Lable
A25: Finance costs | B25: Interest Paid | C25: 30484
A26: NET CASH GENERATED/(USED IN) BY FINANCING ACTIVITIES | B26: =_xlfn.XLOOKUP(A26,CFS_Standalone!A:A,CFS_Standalone!B:B) -> Net Cash Flow From Financing Activities | C26: =_xlfn.XLOOKUP(A26,CFS_Standalone!A:A,CFS_Standalone!C:C) -> 17536
A27: NET INCREASE/(DECREASE) IN CASH AND CASH EQUIVALENTS | B27: =_xlfn.XLOOKUP(A27,CFS_Standalone!A:A,CFS_Standalone!B:B) -> Net increase (decrease) in cash and cash equivalents before effect of exchange rate changes | C27: =_xlfn.XLOOKUP(A27,CFS_Standalone!A:A,CFS_Standalone!C:C) -> 30458
A28: Cash and cash equivalents at the beginning of the year | B28: =_xlfn.XLOOKUP(A28,CFS_Standalone!A:A,CFS_Standalone!B:B) -> Cash and Cash Equivalents at the Beginning of the Year | C28: =_xlfn.XLOOKUP(A28,CFS_Standalone!A:A,CFS_Standalone!C:C) -> 17519
A29: CASH AND CASH EQUIVALENTS AT THE END OF THE YEAR | B29: =_xlfn.XLOOKUP(A29,CFS_Standalone!A:A,CFS_Standalone!B:B) -> Cash and Cash Equivalents at the End of the Year | C29: =_xlfn.XLOOKUP(A29,CFS_Standalone!A:A,CFS_Standalone!C:C) -> 30371

Sheet SR_Standalone
A1: Particulars | B1: Cogencis Field | C1: Field id
A2: Segment Revenue | B2: Lable
A3: Revenue by Geographical Segment | B3: Lable
A4: India | B4: As is Product Name
A5: Outside India | B5: As is Product Name
A6: Total | B6: Segment Revenue | C6: 8920
A7: Less: Inter Segment Revenue | B7: Less: Inter Segment Revenue | C7: 8924
A8: Net sales/Income From Operations | B8: Total Segment Revenue | C8: 8931
A9: Segment Results | B9: Lable
A10: (Profit)(+)/Loss(-) before tax, Other Income & unallocable Expense from each segment) | B10: Lable
A11: India | B11: As is Product Name
A12: Outside India | B12: As is Product Name
A13: Total | B13: Segment Results | C13: 8919
A14: Add: Other Income | B14: Other Income | C14: 14859
A15: Less: Other Un -allocable Exp. | B15: Unallocated Income (Expenses) | C15: 8929
A16: Total Profit Before Tax | B16: Profit/(Loss) from ordinary activities before tax | C16: 8911

Sheet SR_Consolidated
A1: Particulars | B1: Cogencis Field | C1: Field id
A2: Segment Revenue | B2: =_xlfn.XLOOKUP(A2,SR_Standalone!A:A,SR_Standalone!B:B) -> Lable
A3: Revenue by Geographical Segment | B3: =_xlfn.XLOOKUP(A3,SR_Standalone!A:A,SR_Standalone!B:B) -> Lable
A4: India | B4: =_xlfn.XLOOKUP(A4,SR_Standalone!A:A,SR_Standalone!B:B) -> As is Product Name
A5: Outside India | B5: =_xlfn.XLOOKUP(A5,SR_Standalone!A:A,SR_Standalone!B:B) -> As is Product Name
A6: Total | B6: =_xlfn.XLOOKUP(A6,SR_Standalone!A:A,SR_Standalone!B:B) -> Segment Revenue | C6: =_xlfn.XLOOKUP(A6,SR_Standalone!A:A,SR_Standalone!C:C) -> 8920
A7: Less: Inter Segment Revenue | B7: =_xlfn.XLOOKUP(A7,SR_Standalone!A:A,SR_Standalone!B:B) -> Less: Inter Segment Revenue | C7: =_xlfn.XLOOKUP(A7,SR_Standalone!A:A,SR_Standalone!C:C) -> 8924
A8: Net sales/Income From Operations | B8: =_xlfn.XLOOKUP(A8,SR_Standalone!A:A,SR_Standalone!B:B) -> Total Segment Revenue | C8: =_xlfn.XLOOKUP(A8,SR_Standalone!A:A,SR_Standalone!C:C) -> 8931
A9: Segment Results | B9: =_xlfn.XLOOKUP(A9,SR_Standalone!A:A,SR_Standalone!B:B) -> Lable
A10: (Profit)(+)/Loss(-) before tax, interest & unallocable Expense from each segment)* | B10: Lable
A11: India | B11: =_xlfn.XLOOKUP(A11,SR_Standalone!A:A,SR_Standalone!B:B) -> As is Product Name
A12: Outside India | B12: =_xlfn.XLOOKUP(A12,SR_Standalone!A:A,SR_Standalone!B:B) -> As is Product Name
A13: Total | B13: Segment Results | C13: 8919
A14: Add Other Income | B14: Other Income | C14: 14859
A15: Less: Other Un -allocable Exp. | B15: =_xlfn.XLOOKUP(A15,SR_Standalone!A:A,SR_Standalone!B:B) -> Unallocated Income (Expenses) | C15: =_xlfn.XLOOKUP(A15,SR_Standalone!A:A,SR_Standalone!C:C) -> 8929
A16: Total Profit Before Tax | B16: =_xlfn.XLOOKUP(A16,SR_Standalone!A:A,SR_Standalone!B:B) -> Profit/(Loss) from ordinary activities before tax | C16: =_xlfn.XLOOKUP(A16,SR_Standalone!A:A,SR_Standalone!C:C) -> 8911
